pycrowmodule/__init__.py
pycrowmodule/alarm_panel.py
pycrowmodule/crow_base_client.py
pycrowmodule/crow_defs.py
pycrowmodule/status_state.py
pycrowmodule-2024.11.24.dist-info/LICENSE
pycrowmodule-2024.11.24.dist-info/METADATA
pycrowmodule-2024.11.24.dist-info/WHEEL
pycrowmodule-2024.11.24.dist-info/top_level.txt
pycrowmodule-2024.11.24.dist-info/RECORD
